morin/__init__.py
morin/alfacrm_by_date.py
morin/btrx_by_date.py
morin/clickhouse.py
morin/common.py
morin/getcourse_by_date.py
morin/market_by_date.py
morin/mskld_by_date.py
morin/ozon_an_by_date.py
morin/ozon_by_date.py
morin/ozon_reklama.py
morin/sheets.py
morin/vk_by_date.py
morin/wb_by_date.py
morin/wb_reklama.py
morin/yandex_disk_by_page.py
morin/yd_by_date.py
morin/ym_by_date.py
morin-0.4.57.dist-info/LICENSE
morin-0.4.57.dist-info/METADATA
morin-0.4.57.dist-info/WHEEL
morin-0.4.57.dist-info/top_level.txt
morin-0.4.57.dist-info/RECORD
