Metadata-Version: 2.1
Name: morin
Version: 0.4.57
Summary: Помощь в подключениях и загрузке в БД
Home-page: https://github.com/morinad/morin
Author: Александр Морин
Author-email: y.director@yandex.ru
License-File: LICENSE
Requires-Dist: requests
Requires-Dist: clickhouse-connect
Requires-Dist: pandas
Requires-Dist: python-dateutil
